asmscanlstm/__init__.py
asmscanlstm/model.py
asmscanlstm/resources/tokenizer.pickle
asmscanlstm/resources/model/architecture.txt
asmscanlstm/resources/model/config.json
asmscanlstm/resources/model/cvms/bass-model1.h5
asmscanlstm/resources/model/cvms/bass-model2.h5
asmscanlstm/resources/model/cvms/bass-model3.h5
asmscanlstm/resources/model/cvms/bass-model4.h5
asmscanlstm/resources/model/cvms/bass-model5.h5
asmscanlstm/resources/model/cvms/bass-model6.h5
asmscan_lstm-1.0.0.dist-info/LICENSE
asmscan_lstm-1.0.0.dist-info/METADATA
asmscan_lstm-1.0.0.dist-info/WHEEL
asmscan_lstm-1.0.0.dist-info/top_level.txt
asmscan_lstm-1.0.0.dist-info/RECORD
