Metadata-Version: 2.1
Name: asmscan-lstm
Version: 1.0.0
Summary: Bidirectional LSTM model for detection of amyloid signaling motifs.
Home-page: https://github.com/jakub-galazka/asmscan-lstm
Author: Jakub Gałązka
Author-email: kubagalv2@gmail.com
License: GNU General Public License v3 (GPLv3)
Keywords: bidirectional lstm,amyloid signaling motifs
Classifier: Development Status :: 5 - Production/Stable
Classifier: Topic :: Scientific/Engineering :: Bio-Informatics
Classifier: Intended Audience :: Science/Research
Classifier: License :: OSI Approved :: GNU General Public License v3 (GPLv3)
Classifier: Operating System :: OS Independent
Classifier: Programming Language :: Python :: 3.7
Classifier: Programming Language :: Python :: 3.8
Classifier: Programming Language :: Python :: 3.9
Classifier: Programming Language :: Python :: 3.10
Requires-Python: >=3.7
License-File: LICENSE
Requires-Dist: tensorflow (==2.11.0)
Requires-Dist: progress (==1.6)
